[{"Title":"Scary Movie","Year":"2000","imdbID":"tt0175142","Type":"movie"},{"Title":"Scary Movie","Year":"2000","imdbID":"tt0175142","Type":"movie"},{"Title":"Scary Movie 2","Year":"2001","imdbID":"tt0257106","Type":"movie"},{"Title":"Scary Movie 3","Year":"2003","imdbID":"tt0306047","Type":"movie"},{"Title":"Scary Movie 4","Year":"2006","imdbID":"tt0362120","Type":"movie"},{"Title":"Scary Movie 5","Year":"2013","imdbID":"tt0795461","Type":"movie"},{"Title":"Scary or Die","Year":"2012","imdbID":"tt1833879","Type":"movie"},{"Title":"Scary Hair","Year":"2005","imdbID":"tt0475590","Type":"movie"},{"Title":"My Scary Girl","Year":"2006","imdbID":"tt0788052","Type":"movie"},{"Title":"Scary Movie","Year":"1991","imdbID":"tt0138078","Type":"movie"}]